Pipx40/__init__.py
Pipx40-1.33.dist-info/LICENSE.txt
Pipx40-1.33.dist-info/METADATA
Pipx40-1.33.dist-info/WHEEL
Pipx40-1.33.dist-info/top_level.txt
Pipx40-1.33.dist-info/RECORD
