Metadata-Version: 2.1
Name: Pipx40
Version: 1.33
Summary: Python Pipx40 is a Python wrapper for Pickering PXI VISA-compliant driver
Home-page: 
Author: Pickering Interfaces
Author-email: Pickering Interfaces <support@pickeringtest.com>
License: Copyright (c) 2017-2023 Pickering Interfaces Ltd.
Project-URL: homepage, https://downloads.pickeringtest.info/downloads/drivers/PXI_Drivers/
License-File: LICENSE.txt
Requires-Dist: enum34
Requires-Dist: pyvisa
